peakrdl_rust/__init__.py
peakrdl_rust/__peakrdl__.py
peakrdl_rust/component_context.py
peakrdl_rust/crate_generator.py
peakrdl_rust/design_scanner.py
peakrdl_rust/design_state.py
peakrdl_rust/exporter.py
peakrdl_rust/identifier_filter.py
peakrdl_rust/py.typed
peakrdl_rust/templates/.gitignore
peakrdl_rust/templates/Cargo.toml.tmpl
peakrdl_rust/templates/src/access.rs
peakrdl_rust/templates/src/components/addrmap.rs
peakrdl_rust/templates/src/components/enum.rs
peakrdl_rust/templates/src/components/macros.jinja2
peakrdl_rust/templates/src/components/memory.rs
peakrdl_rust/templates/src/components/register.rs
peakrdl_rust/templates/src/components.rs
peakrdl_rust/templates/src/encode.rs
peakrdl_rust/templates/src/fixedpoint.rs
peakrdl_rust/templates/src/lib.rs
peakrdl_rust/templates/src/mem.rs
peakrdl_rust/templates/src/reg.rs
peakrdl_rust/templates/tests/test_addrmap.rs
peakrdl_rust/test_generator.py
peakrdl_rust/udps/__init__.py
peakrdl_rust/udps/fixedpoint.py
peakrdl_rust/udps/signed.py
peakrdl_rust/udps/udps.rdl
peakrdl_rust/utils.py
peakrdl_rust-0.5.1.dist-info/WHEEL
peakrdl_rust-0.5.1.dist-info/entry_points.txt
peakrdl_rust-0.5.1.dist-info/METADATA
peakrdl_rust-0.5.1.dist-info/RECORD
