Metadata-Version: 2.4
Name: peakrdl-rust
Version: 0.5.1
Summary: Generate a Rust crate from SystemRDL for accessing control/status registers.
Keywords: SystemRDL,PeakRDL,CSR,compiler,tool,registers,generator,Rust,PAC,embedded
Author: Dana Sorensen
Author-email: Dana Sorensen <dana.r.sorensen@gmail.com>
License-Expression: LGPL-2.1-or-later
Classifier: Development Status :: 4 - Beta
Classifier: Environment :: Plugins
Classifier: License :: OSI Approved :: GNU Lesser General Public License v2 (LGPLv2)
Classifier: Operating System :: OS Independent
Classifier: Programming Language :: Python :: 3
Classifier: Programming Language :: Python :: 3 :: Only
Classifier: Programming Language :: Python :: 3.9
Classifier: Programming Language :: Python :: 3.10
Classifier: Programming Language :: Python :: 3.11
Classifier: Programming Language :: Python :: 3.12
Classifier: Programming Language :: Python :: 3.13
Classifier: Programming Language :: Python :: 3.14
Classifier: Programming Language :: Rust
Classifier: Topic :: Scientific/Engineering :: Electronic Design Automation (EDA)
Classifier: Typing :: Typed
Requires-Dist: case-converter>=1.2.0
Requires-Dist: jinja2>=3.1.6
Requires-Dist: systemrdl-compiler>=1.29.3
Requires-Dist: peakrdl-cli>=1.4.0 ; extra == 'cli'
Requires-Python: >=3.9
Project-URL: Changelog, https://github.com/darsor/PeakRDL-rust/blob/main/CHANGELOG.md
Project-URL: Documentation, https://peakrdl-rust.readthedocs.io/
Project-URL: Source, https://github.com/darsor/PeakRDL-rust
Project-URL: Tracker, https://github.com/darsor/PeakRDL-rust/issues
Provides-Extra: cli
